sserender/__init__.py
sserender/sse.py
sserender-0.0.3.dist-info/LICENSE
sserender-0.0.3.dist-info/METADATA
sserender-0.0.3.dist-info/WHEEL
sserender-0.0.3.dist-info/top_level.txt
sserender-0.0.3.dist-info/RECORD
