Metadata-Version: 2.1
Name: sserender
Version: 0.0.3
Summary: sse message render
Home-page: UNKNOWN
Author: hsz
Author-email: hsz1273327@gmail.com
License: MIT License
Keywords: sse
Platform: UNKNOWN
Classifier: License :: OSI Approved :: MIT License
Classifier: Programming Language :: Python :: 3.7
Classifier: Programming Language :: Python :: 3.8
Classifier: Programming Language :: Python :: 3.9
Requires-Dist: mypy (>=0.800)
